{
	"id": "credenciados",
	"realm": "credenciados",
	"notBefore": 0,
	"revokeRefreshToken": false,
	"refreshTokenMaxReuse": 0,
	"accessTokenLifespan": 300,
	"accessTokenLifespanForImplicitFlow": 900,
	"ssoSessionIdleTimeout": 1800,
	"ssoSessionMaxLifespan": 36000,
	"ssoSessionIdleTimeoutRememberMe": 0,
	"ssoSessionMaxLifespanRememberMe": 0,
	"offlineSessionIdleTimeout": 2592000,
	"offlineSessionMaxLifespanEnabled": false,
	"offlineSessionMaxLifespan": 5184000,
	"clientSessionIdleTimeout": 0,
	"clientSessionMaxLifespan": 0,
	"clientOfflineSessionIdleTimeout": 0,
	"clientOfflineSessionMaxLifespan": 0,
	"accessCodeLifespan": 60,
	"accessCodeLifespanUserAction": 300,
	"accessCodeLifespanLogin": 1800,
	"actionTokenGeneratedByAdminLifespan": 43200,
	"actionTokenGeneratedByUserLifespan": 300,
	"enabled": true,
	"sslRequired": "external",
	"registrationAllowed": false,
	"registrationEmailAsUsername": false,
	"rememberMe": false,
	"verifyEmail": false,
	"loginWithEmailAllowed": true,
	"duplicateEmailsAllowed": false,
	"resetPasswordAllowed": false,
	"editUsernameAllowed": false,
	"bruteForceProtected": false,
	"permanentLockout": false,
	"maxFailureWaitSeconds": 900,
	"minimumQuickLoginWaitSeconds": 60,
	"waitIncrementSeconds": 60,
	"quickLoginCheckMilliSeconds": 1000,
	"maxDeltaTimeSeconds": 43200,
	"failureFactor": 30,
	"roles": {
		"realm": [
			{
				"id": "754c9a94-d13a-4465-937a-f39598f2df7c",
				"name": "administrativo",
				"composite": false,
				"clientRole": false,
				"containerId": "credenciados",
				"attributes": {}
			},
			{
				"id": "6c08e97b-43bf-4560-b8c1-8dc067885868",
				"name": "offline_access",
				"description": "${role_offline-access}",
				"composite": false,
				"clientRole": false,
				"containerId": "credenciados",
				"attributes": {}
			},
			{
				"id": "52a82f84-863f-4734-a128-19884d5b9798",
				"name": "operacional",
				"composite": false,
				"clientRole": false,
				"containerId": "credenciados",
				"attributes": {}
			},
			{
				"id": "7b91fa4a-f125-41b3-9684-a4fbdfb90c53",
				"name": "uma_authorization",
				"composite": false,
				"clientRole": false,
				"containerId": "credenciados",
				"attributes": {}
			},
			{
				"id": "289a5fa5-cb36-4dec-b876-e619b147742b",
				"name": "administrador",
				"composite": false,
				"clientRole": false,
				"containerId": "credenciados",
				"attributes": {}
			}
		],
		"client": {
			"realm-management": [
				{
					"id": "2aadfa59-9c37-4985-aaa3-fd71b40928a5",
					"name": "manage-clients",
					"description": "${role_manage-clients}",
					"composite": false,
					"clientRole": true,
					"containerId": "e7a2e181-bd66-4ff7-943f-babbb98fbfdb",
					"attributes": {}
				},
				{
					"id": "2b02852c-d243-4440-8283-7e15549a5d80",
					"name": "create-client",
					"description": "${role_create-client}",
					"composite": false,
					"clientRole": true,
					"containerId": "e7a2e181-bd66-4ff7-943f-babbb98fbfdb",
					"attributes": {}
				},
				{
					"id": "4d3130d5-065e-408a-820c-c8c5005f309a",
					"name": "manage-realm",
					"description": "${role_manage-realm}",
					"composite": false,
					"clientRole": true,
					"containerId": "e7a2e181-bd66-4ff7-943f-babbb98fbfdb",
					"attributes": {}
				},
				{
					"id": "b1ba2b9e-7e85-4f0e-b648-a048864a6502",
					"name": "view-events",
					"description": "${role_view-events}",
					"composite": false,
					"clientRole": true,
					"containerId": "e7a2e181-bd66-4ff7-943f-babbb98fbfdb",
					"attributes": {}
				},
				{
					"id": "7b008d3a-3e35-4af0-8995-c1d1ad615922",
					"name": "view-identity-providers",
					"description": "${role_view-identity-providers}",
					"composite": false,
					"clientRole": true,
					"containerId": "e7a2e181-bd66-4ff7-943f-babbb98fbfdb",
					"attributes": {}
				},
				{
					"id": "8aad8d50-ef41-4eda-a193-d0aaf3049343",
					"name": "view-realm",
					"description": "${role_view-realm}",
					"composite": false,
					"clientRole": true,
					"containerId": "e7a2e181-bd66-4ff7-943f-babbb98fbfdb",
					"attributes": {}
				},
				{
					"id": "c95e44fd-1b83-47d0-9274-0002bf283dd7",
					"name": "realm-admin",
					"description": "${role_realm-admin}",
					"composite": true,
					"composites": {
						"client": {
							"realm-management": [
								"manage-clients",
								"create-client",
								"view-events",
								"manage-realm",
								"view-identity-providers",
								"view-realm",
								"manage-events",
								"manage-identity-providers",
								"impersonation",
								"query-clients",
								"query-realms",
								"view-clients",
								"query-groups",
								"view-authorization",
								"query-users",
								"manage-authorization",
								"manage-users",
								"view-users"
							]
						}
					},
					"clientRole": true,
					"containerId": "e7a2e181-bd66-4ff7-943f-babbb98fbfdb",
					"attributes": {}
				},
				{
					"id": "d86b7968-c35a-4520-a226-2ece4db20a28",
					"name": "manage-events",
					"description": "${role_manage-events}",
					"composite": false,
					"clientRole": true,
					"containerId": "e7a2e181-bd66-4ff7-943f-babbb98fbfdb",
					"attributes": {}
				},
				{
					"id": "ae65fae7-3b11-4442-b4ee-b79d1cf30e6e",
					"name": "manage-identity-providers",
					"description": "${role_manage-identity-providers}",
					"composite": false,
					"clientRole": true,
					"containerId": "e7a2e181-bd66-4ff7-943f-babbb98fbfdb",
					"attributes": {}
				},
				{
					"id": "4d09143b-8b74-4782-9a7e-0c6cf68daca4",
					"name": "impersonation",
					"description": "${role_impersonation}",
					"composite": false,
					"clientRole": true,
					"containerId": "e7a2e181-bd66-4ff7-943f-babbb98fbfdb",
					"attributes": {}
				},
				{
					"id": "0bad4183-729f-48ea-b134-63d3f249e90a",
					"name": "query-clients",
					"description": "${role_query-clients}",
					"composite": false,
					"clientRole": true,
					"containerId": "e7a2e181-bd66-4ff7-943f-babbb98fbfdb",
					"attributes": {}
				},
				{
					"id": "7cd5ce3a-ccb5-4f9d-9cf9-c5eaaeb53f1e",
					"name": "query-realms",
					"description": "${role_query-realms}",
					"composite": false,
					"clientRole": true,
					"containerId": "e7a2e181-bd66-4ff7-943f-babbb98fbfdb",
					"attributes": {}
				},
				{
					"id": "f8d874b6-c53c-4e80-a849-eb5ddf40a541",
					"name": "query-groups",
					"description": "${role_query-groups}",
					"composite": false,
					"clientRole": true,
					"containerId": "e7a2e181-bd66-4ff7-943f-babbb98fbfdb",
					"attributes": {}
				},
				{
					"id": "1ff969c1-185e-4f5e-ab20-e12bcee992c1",
					"name": "view-clients",
					"description": "${role_view-clients}",
					"composite": true,
					"composites": {
						"client": {
							"realm-management": ["query-clients"]
						}
					},
					"clientRole": true,
					"containerId": "e7a2e181-bd66-4ff7-943f-babbb98fbfdb",
					"attributes": {}
				},
				{
					"id": "d97150bf-eec7-40e2-84cf-199e4df9a6a8",
					"name": "query-users",
					"description": "${role_query-users}",
					"composite": false,
					"clientRole": true,
					"containerId": "e7a2e181-bd66-4ff7-943f-babbb98fbfdb",
					"attributes": {}
				},
				{
					"id": "8cfcc1e5-775f-4657-a795-80ec87caae1a",
					"name": "view-authorization",
					"description": "${role_view-authorization}",
					"composite": false,
					"clientRole": true,
					"containerId": "e7a2e181-bd66-4ff7-943f-babbb98fbfdb",
					"attributes": {}
				},
				{
					"id": "4178a50d-6b52-469e-95f8-c40305a9f1b1",
					"name": "manage-authorization",
					"description": "${role_manage-authorization}",
					"composite": false,
					"clientRole": true,
					"containerId": "e7a2e181-bd66-4ff7-943f-babbb98fbfdb",
					"attributes": {}
				},
				{
					"id": "c5d89924-79b7-441d-a03f-d5b61bdc60d6",
					"name": "manage-users",
					"description": "${role_manage-users}",
					"composite": false,
					"clientRole": true,
					"containerId": "e7a2e181-bd66-4ff7-943f-babbb98fbfdb",
					"attributes": {}
				},
				{
					"id": "f9970fb3-7c11-43e9-81b2-b963e9fc3510",
					"name": "view-users",
					"description": "${role_view-users}",
					"composite": true,
					"composites": {
						"client": {
							"realm-management": ["query-groups", "query-users"]
						}
					},
					"clientRole": true,
					"containerId": "e7a2e181-bd66-4ff7-943f-babbb98fbfdb",
					"attributes": {}
				}
			],
			"credenciados-gateway": [],
			"security-admin-console": [],
			"admin-cli": [],
			"account-console": [],
			"broker": [],
			"account": [
				{
					"id": "c176d6ae-ee87-4ca7-aa9b-fa2a9947a423",
					"name": "view-profile",
					"composite": false,
					"clientRole": true,
					"containerId": "7dd731e1-82ed-422b-82a1-e4fbc3c3b84b",
					"attributes": {}
				},
				{
					"id": "c25c6d5b-4aff-41fb-a6d3-fb57ad2d8058",
					"name": "delete-account",
					"description": "${role_delete-account}",
					"composite": false,
					"clientRole": true,
					"containerId": "7dd731e1-82ed-422b-82a1-e4fbc3c3b84b",
					"attributes": {}
				},
				{
					"id": "4c052933-751f-4eb2-8591-3df915ca7fd2",
					"name": "manage-account",
					"composite": false,
					"clientRole": true,
					"containerId": "7dd731e1-82ed-422b-82a1-e4fbc3c3b84b",
					"attributes": {}
				}
			]
		}
	},
	"groups": [
		{
			"id": "68d4287f-8fb5-426c-a48f-67f5c60f24ef",
			"name": "administradores-postos-av-brasil",
			"path": "/administradores-postos-av-brasil",
			"attributes": {},
			"realmRoles": ["administrativo"],
			"clientRoles": {},
			"subGroups": []
		},
		{
			"id": "12323ead-edab-4eea-8f2f-4eb9bdbf1bda",
			"name": "frentistas-postos-av-brasil",
			"path": "/frentistas-postos-av-brasil",
			"attributes": {},
			"realmRoles": ["operacional"],
			"clientRoles": {},
			"subGroups": []
		}
	],
	"defaultRoles": ["offline_access", "uma_authorization"],
	"requiredCredentials": ["password"],
	"otpPolicyType": "totp",
	"otpPolicyAlgorithm": "HmacSHA1",
	"otpPolicyInitialCounter": 0,
	"otpPolicyDigits": 6,
	"otpPolicyLookAheadWindow": 1,
	"otpPolicyPeriod": 30,
	"otpSupportedApplications": ["FreeOTP", "Google Authenticator"],
	"webAuthnPolicyRpEntityName": "keycloak",
	"webAuthnPolicySignatureAlgorithms": ["ES256"],
	"webAuthnPolicyRpId": "",
	"webAuthnPolicyAttestationConveyancePreference": "not specified",
	"webAuthnPolicyAuthenticatorAttachment": "not specified",
	"webAuthnPolicyRequireResidentKey": "not specified",
	"webAuthnPolicyUserVerificationRequirement": "not specified",
	"webAuthnPolicyCreateTimeout": 0,
	"webAuthnPolicyAvoidSameAuthenticatorRegister": false,
	"webAuthnPolicyAcceptableAaguids": [],
	"webAuthnPolicyPasswordlessRpEntityName": "keycloak",
	"webAuthnPolicyPasswordlessSignatureAlgorithms": ["ES256"],
	"webAuthnPolicyPasswordlessRpId": "",
	"webAuthnPolicyPasswordlessAttestationConveyancePreference": "not specified",
	"webAuthnPolicyPasswordlessAuthenticatorAttachment": "not specified",
	"webAuthnPolicyPasswordlessRequireResidentKey": "not specified",
	"webAuthnPolicyPasswordlessUserVerificationRequirement": "not specified",
	"webAuthnPolicyPasswordlessCreateTimeout": 0,
	"webAuthnPolicyPasswordlessAvoidSameAuthenticatorRegister": false,
	"webAuthnPolicyPasswordlessAcceptableAaguids": [],
	"users": [
		{
			"id": "db57b52e-53ea-4d50-9140-4d051f4655e1",
			"createdTimestamp": 1617060798725,
			"username": "service-account-credenciados-gateway",
			"enabled": true,
			"totp": false,
			"emailVerified": false,
			"serviceAccountClientId": "credenciados-gateway",
			"disableableCredentialTypes": [],
			"requiredActions": [],
			"clientRoles": {
				"realm-management": [
					"query-groups",
					"query-users",
					"view-authorization",
					"manage-authorization",
					"manage-users",
					"view-users"
				]
			},
			"notBefore": 0,
			"groups": []
		}
	],
	"scopeMappings": [
		{
			"clientScope": "offline_access",
			"roles": ["offline_access"]
		}
	],
	"clientScopeMappings": {
		"account": [
			{
				"client": "account-console",
				"roles": ["manage-account"]
			}
		]
	},
	"clients": [
		{
			"id": "7dd731e1-82ed-422b-82a1-e4fbc3c3b84b",
			"clientId": "account",
			"name": "${client_account}",
			"rootUrl": "${authBaseUrl}",
			"baseUrl": "/realms/credenciados/account/",
			"surrogateAuthRequired": false,
			"enabled": true,
			"alwaysDisplayInConsole": false,
			"clientAuthenticatorType": "client-secret",
			"secret": "**********",
			"defaultRoles": ["view-profile", "manage-account"],
			"redirectUris": ["/realms/credenciados/account/*"],
			"webOrigins": [],
			"notBefore": 0,
			"bearerOnly": false,
			"consentRequired": false,
			"standardFlowEnabled": true,
			"implicitFlowEnabled": false,
			"directAccessGrantsEnabled": false,
			"serviceAccountsEnabled": false,
			"publicClient": false,
			"frontchannelLogout": false,
			"protocol": "openid-connect",
			"attributes": {},
			"authenticationFlowBindingOverrides": {},
			"fullScopeAllowed": false,
			"nodeReRegistrationTimeout": 0,
			"defaultClientScopes": [
				"web-origins",
				"role_list",
				"roles",
				"profile",
				"email"
			],
			"optionalClientScopes": [
				"address",
				"phone",
				"offline_access",
				"microprofile-jwt"
			]
		},
		{
			"id": "5279d6d3-e924-4d2f-8d7b-03345ce4219b",
			"clientId": "account-console",
			"name": "${client_account-console}",
			"rootUrl": "${authBaseUrl}",
			"baseUrl": "/realms/credenciados/account/",
			"surrogateAuthRequired": false,
			"enabled": true,
			"alwaysDisplayInConsole": false,
			"clientAuthenticatorType": "client-secret",
			"secret": "**********",
			"redirectUris": ["/realms/credenciados/account/*"],
			"webOrigins": [],
			"notBefore": 0,
			"bearerOnly": false,
			"consentRequired": false,
			"standardFlowEnabled": true,
			"implicitFlowEnabled": false,
			"directAccessGrantsEnabled": false,
			"serviceAccountsEnabled": false,
			"publicClient": true,
			"frontchannelLogout": false,
			"protocol": "openid-connect",
			"attributes": {
				"pkce.code.challenge.method": "S256"
			},
			"authenticationFlowBindingOverrides": {},
			"fullScopeAllowed": false,
			"nodeReRegistrationTimeout": 0,
			"protocolMappers": [
				{
					"id": "e52971f2-009b-4412-942c-660f257f7fe8",
					"name": "audience resolve",
					"protocol": "openid-connect",
					"protocolMapper": "oidc-audience-resolve-mapper",
					"consentRequired": false,
					"config": {}
				}
			],
			"defaultClientScopes": [
				"web-origins",
				"role_list",
				"roles",
				"profile",
				"email"
			],
			"optionalClientScopes": [
				"address",
				"phone",
				"offline_access",
				"microprofile-jwt"
			]
		},
		{
			"id": "1a335947-f78c-4d4f-a48f-d7cef6edbd01",
			"clientId": "admin-cli",
			"name": "${client_admin-cli}",
			"surrogateAuthRequired": false,
			"enabled": true,
			"alwaysDisplayInConsole": false,
			"clientAuthenticatorType": "client-secret",
			"secret": "**********",
			"redirectUris": [],
			"webOrigins": [],
			"notBefore": 0,
			"bearerOnly": false,
			"consentRequired": false,
			"standardFlowEnabled": false,
			"implicitFlowEnabled": false,
			"directAccessGrantsEnabled": true,
			"serviceAccountsEnabled": false,
			"publicClient": true,
			"frontchannelLogout": false,
			"protocol": "openid-connect",
			"attributes": {},
			"authenticationFlowBindingOverrides": {},
			"fullScopeAllowed": false,
			"nodeReRegistrationTimeout": 0,
			"defaultClientScopes": [
				"web-origins",
				"role_list",
				"roles",
				"profile",
				"email"
			],
			"optionalClientScopes": [
				"address",
				"phone",
				"offline_access",
				"microprofile-jwt"
			]
		},
		{
			"id": "a6eadf3a-1d1b-4b67-94e9-a395a430bf79",
			"clientId": "broker",
			"name": "${client_broker}",
			"surrogateAuthRequired": false,
			"enabled": true,
			"alwaysDisplayInConsole": false,
			"clientAuthenticatorType": "client-secret",
			"secret": "**********",
			"redirectUris": [],
			"webOrigins": [],
			"notBefore": 0,
			"bearerOnly": false,
			"consentRequired": false,
			"standardFlowEnabled": true,
			"implicitFlowEnabled": false,
			"directAccessGrantsEnabled": false,
			"serviceAccountsEnabled": false,
			"publicClient": false,
			"frontchannelLogout": false,
			"protocol": "openid-connect",
			"attributes": {},
			"authenticationFlowBindingOverrides": {},
			"fullScopeAllowed": false,
			"nodeReRegistrationTimeout": 0,
			"defaultClientScopes": [
				"web-origins",
				"role_list",
				"roles",
				"profile",
				"email"
			],
			"optionalClientScopes": [
				"address",
				"phone",
				"offline_access",
				"microprofile-jwt"
			]
		},
		{
			"id": "4e258635-036c-4618-85f0-33f621167a12",
			"clientId": "credenciados-gateway",
			"rootUrl": "http://localhost:3000",
			"adminUrl": "http://localhost:3000",
			"surrogateAuthRequired": false,
			"enabled": true,
			"alwaysDisplayInConsole": false,
			"clientAuthenticatorType": "client-secret",
			"secret": "8e78b3a5-26bd-48c6-8c6d-ce54b4cbef0d",
			"redirectUris": ["http://localhost:3000/*"],
			"webOrigins": ["http://localhost:3000"],
			"notBefore": 0,
			"bearerOnly": false,
			"consentRequired": false,
			"standardFlowEnabled": true,
			"implicitFlowEnabled": false,
			"directAccessGrantsEnabled": true,
			"serviceAccountsEnabled": true,
			"authorizationServicesEnabled": true,
			"publicClient": false,
			"frontchannelLogout": false,
			"protocol": "openid-connect",
			"attributes": {
				"saml.assertion.signature": "false",
				"saml.force.post.binding": "false",
				"saml.multivalued.roles": "false",
				"saml.encrypt": "false",
				"backchannel.logout.revoke.offline.tokens": "false",
				"saml.server.signature": "false",
				"saml.server.signature.keyinfo.ext": "false",
				"exclude.session.state.from.auth.response": "false",
				"backchannel.logout.session.required": "false",
				"client_credentials.use_refresh_token": "false",
				"saml_force_name_id_format": "false",
				"saml.client.signature": "false",
				"tls.client.certificate.bound.access.tokens": "false",
				"saml.authnstatement": "false",
				"display.on.consent.screen": "false",
				"saml.onetimeuse.condition": "false"
			},
			"authenticationFlowBindingOverrides": {},
			"fullScopeAllowed": true,
			"nodeReRegistrationTimeout": -1,
			"protocolMappers": [
				{
					"id": "ca1caf21-d922-4351-963d-662a0c2867bb",
					"name": "Client IP Address",
					"protocol": "openid-connect",
					"protocolMapper": "oidc-usersessionmodel-note-mapper",
					"consentRequired": false,
					"config": {
						"user.session.note": "clientAddress",
						"userinfo.token.claim": "true",
						"id.token.claim": "true",
						"access.token.claim": "true",
						"claim.name": "clientAddress",
						"jsonType.label": "String"
					}
				},
				{
					"id": "e5c3fae6-42e4-4ad7-a7be-8c4b7a3d67ae",
					"name": "Client ID",
					"protocol": "openid-connect",
					"protocolMapper": "oidc-usersessionmodel-note-mapper",
					"consentRequired": false,
					"config": {
						"user.session.note": "clientId",
						"userinfo.token.claim": "true",
						"id.token.claim": "true",
						"access.token.claim": "true",
						"claim.name": "clientId",
						"jsonType.label": "String"
					}
				},
				{
					"id": "954ed576-8cd0-42e6-9ca6-7be2b1aedcd1",
					"name": "Client Host",
					"protocol": "openid-connect",
					"protocolMapper": "oidc-usersessionmodel-note-mapper",
					"consentRequired": false,
					"config": {
						"user.session.note": "clientHost",
						"userinfo.token.claim": "true",
						"id.token.claim": "true",
						"access.token.claim": "true",
						"claim.name": "clientHost",
						"jsonType.label": "String"
					}
				}
			],
			"defaultClientScopes": [
				"web-origins",
				"role_list",
				"roles",
				"profile",
				"email"
			],
			"optionalClientScopes": [
				"address",
				"phone",
				"offline_access",
				"microprofile-jwt"
			],
			"authorizationSettings": {
				"allowRemoteResourceManagement": true,
				"policyEnforcementMode": "ENFORCING",
				"resources": [
					{
						"name": "Default Resource",
						"type": "urn:credenciadosGateway:resources:default",
						"ownerManagedAccess": false,
						"attributes": {},
						"_id": "1bf3b737-1680-48c8-94cd-1fadf6843949",
						"uris": ["/*"]
					},
					{
						"name": "grupo-usuario",
						"ownerManagedAccess": false,
						"displayName": "grupo-usuario",
						"attributes": {},
						"_id": "a95e067d-f44e-4ed3-a239-0adcf322c892",
						"uris": ["/grupo-usuario/*"],
						"scopes": [
							{
								"name": "visualizar"
							},
							{
								"name": "gerenciar"
							}
						]
					},
					{
						"name": "authexcept",
						"ownerManagedAccess": false,
						"displayName": "authexcept",
						"attributes": {},
						"_id": "50bc463e-af01-4f78-a235-4ad0c939e4c5",
						"uris": ["/authexcept/*"],
						"scopes": [
							{
								"name": "visualizar"
							},
							{
								"name": "gerenciar"
							}
						]
					},
					{
						"name": "comportamento",
						"ownerManagedAccess": false,
						"displayName": "comportamento",
						"attributes": {},
						"_id": "c6340286-4efd-4be6-be5a-2b40906c83ab",
						"uris": ["/comportamento/*"],
						"scopes": [
							{
								"name": "visualizar"
							},
							{
								"name": "gerenciar"
							}
						]
					},
					{
						"name": "funcionalidade",
						"ownerManagedAccess": false,
						"displayName": "funcionalidade",
						"attributes": {},
						"_id": "504443bb-725e-46e2-bfad-3a56945fe9f9",
						"uris": ["/funcionalidade/*"],
						"scopes": [
							{
								"name": "visualizar"
							},
							{
								"name": "gerenciar"
							}
						]
					},
					{
						"name": "grupo-credenciado",
						"ownerManagedAccess": false,
						"displayName": "grupo-credenciado",
						"attributes": {},
						"_id": "a43efa33-146b-459d-a177-a79e3cc35017",
						"uris": ["/grupo-credenciado/*"],
						"scopes": [
							{
								"name": "visualizar"
							},
							{
								"name": "gerenciar"
							}
						]
					},
					{
						"name": "perfil",
						"ownerManagedAccess": false,
						"displayName": "perfil",
						"attributes": {},
						"_id": "12c29400-f257-4d6d-9066-fbd6b1b2b732",
						"uris": ["/perfil/*"],
						"scopes": [
							{
								"name": "visualizar"
							},
							{
								"name": "gerenciar"
							}
						]
					},
					{
						"name": "razao-uso",
						"ownerManagedAccess": false,
						"displayName": "razao-uso",
						"attributes": {},
						"_id": "12c17b6c-d410-4c82-843e-077c3a9c7473",
						"uris": ["/razao-uso/*"],
						"scopes": [
							{
								"name": "visualizar"
							},
							{
								"name": "gerenciar"
							}
						]
					},
					{
						"name": "recurso",
						"ownerManagedAccess": false,
						"displayName": "recurso",
						"attributes": {},
						"_id": "1a47e71f-113f-414d-86cf-cb1d9acd66cc",
						"uris": ["/recurso/*"],
						"scopes": [
							{
								"name": "visualizar"
							},
							{
								"name": "gerenciar"
							}
						]
					},
					{
						"name": "repasse",
						"ownerManagedAccess": false,
						"displayName": "repasse",
						"attributes": {},
						"_id": "7d039725-3821-4a7f-be05-5f660e378d14",
						"uris": ["/repasse/*"],
						"scopes": [
							{
								"name": "visualizar"
							},
							{
								"name": "gerenciar"
							}
						]
					},
					{
						"name": "transacao",
						"ownerManagedAccess": false,
						"displayName": "transacao",
						"attributes": {},
						"_id": "e9696aa1-0ccf-4e18-af7a-c827cc25575d",
						"uris": ["/transacao/*"],
						"scopes": [
							{
								"name": "visualizar"
							},
							{
								"name": "gerenciar"
							}
						]
					},
					{
						"name": "usuario",
						"ownerManagedAccess": false,
						"displayName": "usuario",
						"attributes": {},
						"_id": "07b4c287-9919-4896-b3dc-41a0ab8f4302",
						"uris": ["/usuario/*"],
						"scopes": [
							{
								"name": "visualizar"
							},
							{
								"name": "gerenciar"
							}
						]
					},
					{
						"name": "credenciado",
						"ownerManagedAccess": false,
						"displayName": "credenciado",
						"attributes": {},
						"_id": "1c4c7f77-bcba-450e-a521-c6929fbfa8b4",
						"uris": ["/credenciado/*"],
						"scopes": [
							{
								"name": "visualizar"
							},
							{
								"name": "gerenciar"
							}
						]
					}
				],
				"policies": [
					{
						"id": "8a97759c-263a-4c11-aaeb-c4cc7d831531",
						"name": "Default Policy",
						"description": "A policy that grants access only for users within this realm",
						"type": "js",
						"logic": "POSITIVE",
						"decisionStrategy": "AFFIRMATIVE",
						"config": {
							"code": "// by default, grants any permission associated with this policy\n$evaluation.grant();\n"
						}
					},
					{
						"id": "ff8dca80-f40a-4949-a140-8b82e3a2cbf7",
						"name": "Somente Administrador e Administrativo Policy",
						"description": "Somente Administrador e Administrativo Policy",
						"type": "role",
						"logic": "POSITIVE",
						"decisionStrategy": "UNANIMOUS",
						"config": {
							"roles": "[{\"id\":\"administrador\",\"required\":false},{\"id\":\"administrativo\",\"required\":false}]"
						}
					},
					{
						"id": "15fc067a-dc68-44be-aafa-db1490cc1615",
						"name": "Somente Operacional Policy",
						"description": "Somente Operacional Policy",
						"type": "role",
						"logic": "POSITIVE",
						"decisionStrategy": "UNANIMOUS",
						"config": {
							"roles": "[{\"id\":\"operacional\",\"required\":false}]"
						}
					},
					{
						"id": "036a7e58-f8ba-4b05-a02b-c31f4c1ed0c3",
						"name": "Somente Administrador Policy",
						"description": "Somente Administrador Policy",
						"type": "role",
						"logic": "POSITIVE",
						"decisionStrategy": "UNANIMOUS",
						"config": {
							"roles": "[{\"id\":\"administrador\",\"required\":false}]"
						}
					},
					{
						"id": "d2acac23-ffd5-4b75-abdc-e2f12c71ef7a",
						"name": "Somente Administrativo Policy",
						"description": "Somente Administrativo Policy",
						"type": "role",
						"logic": "POSITIVE",
						"decisionStrategy": "UNANIMOUS",
						"config": {
							"roles": "[{\"id\":\"administrativo\",\"required\":false}]"
						}
					},
					{
						"id": "4d797f57-80fa-45b6-a2ca-612106a3abd5",
						"name": "authexcept:visualizar",
						"description": "authexcept:visualizar",
						"type": "scope",
						"logic": "POSITIVE",
						"decisionStrategy": "UNANIMOUS",
						"config": {
							"resources": "[\"authexcept\"]",
							"scopes": "[\"visualizar\"]",
							"applyPolicies": "[\"Somente Operacional Policy\"]"
						}
					},
					{
						"id": "6bc842fa-8ede-4a89-8d4d-fd40fe5ccdef",
						"name": "grupo-usuario:visualizar",
						"description": "grupo-usuario:visualizar",
						"type": "scope",
						"logic": "POSITIVE",
						"decisionStrategy": "UNANIMOUS",
						"config": {
							"resources": "[\"grupo-usuario\"]",
							"scopes": "[\"visualizar\"]",
							"applyPolicies": "[\"Somente Administrador e Administrativo Policy\"]"
						}
					},
					{
						"id": "022e58d6-2d45-4ac4-957d-8515a5cf3bb3",
						"name": "grupo-usuario:gerenciar",
						"description": "grupo-usuario:gerenciar",
						"type": "scope",
						"logic": "POSITIVE",
						"decisionStrategy": "UNANIMOUS",
						"config": {
							"resources": "[\"grupo-usuario\"]",
							"scopes": "[\"gerenciar\",\"visualizar\"]",
							"applyPolicies": "[\"Somente Administrador e Administrativo Policy\"]"
						}
					},
					{
						"id": "1a6e5ec4-6f37-41fd-962c-2eedecaf1544",
						"name": "authexcept:gerenciar",
						"description": "authexcept:gerenciar",
						"type": "scope",
						"logic": "POSITIVE",
						"decisionStrategy": "UNANIMOUS",
						"config": {
							"resources": "[\"authexcept\"]",
							"scopes": "[\"gerenciar\",\"visualizar\"]",
							"applyPolicies": "[\"Somente Administrador e Administrativo Policy\"]"
						}
					}
				],
				"scopes": [
					{
						"id": "d35630d7-b61d-4a90-983b-298a85c54110",
						"name": "gerenciar"
					},
					{
						"id": "e122608a-1e5e-41f8-8fcd-84b05fafab8b",
						"name": "visualizar"
					}
				],
				"decisionStrategy": "UNANIMOUS"
			}
		},
		{
			"id": "e7a2e181-bd66-4ff7-943f-babbb98fbfdb",
			"clientId": "realm-management",
			"name": "${client_realm-management}",
			"surrogateAuthRequired": false,
			"enabled": true,
			"alwaysDisplayInConsole": false,
			"clientAuthenticatorType": "client-secret",
			"secret": "**********",
			"redirectUris": [],
			"webOrigins": [],
			"notBefore": 0,
			"bearerOnly": true,
			"consentRequired": false,
			"standardFlowEnabled": true,
			"implicitFlowEnabled": false,
			"directAccessGrantsEnabled": false,
			"serviceAccountsEnabled": false,
			"publicClient": false,
			"frontchannelLogout": false,
			"protocol": "openid-connect",
			"attributes": {},
			"authenticationFlowBindingOverrides": {},
			"fullScopeAllowed": false,
			"nodeReRegistrationTimeout": 0,
			"defaultClientScopes": [
				"web-origins",
				"role_list",
				"roles",
				"profile",
				"email"
			],
			"optionalClientScopes": [
				"address",
				"phone",
				"offline_access",
				"microprofile-jwt"
			]
		},
		{
			"id": "983f5add-ee04-49f0-81f2-5e9cdb4070e7",
			"clientId": "security-admin-console",
			"name": "${client_security-admin-console}",
			"rootUrl": "${authAdminUrl}",
			"baseUrl": "/admin/credenciados/console/",
			"surrogateAuthRequired": false,
			"enabled": true,
			"alwaysDisplayInConsole": false,
			"clientAuthenticatorType": "client-secret",
			"secret": "**********",
			"redirectUris": ["/admin/credenciados/console/*"],
			"webOrigins": ["+"],
			"notBefore": 0,
			"bearerOnly": false,
			"consentRequired": false,
			"standardFlowEnabled": true,
			"implicitFlowEnabled": false,
			"directAccessGrantsEnabled": false,
			"serviceAccountsEnabled": false,
			"publicClient": true,
			"frontchannelLogout": false,
			"protocol": "openid-connect",
			"attributes": {
				"pkce.code.challenge.method": "S256"
			},
			"authenticationFlowBindingOverrides": {},
			"fullScopeAllowed": false,
			"nodeReRegistrationTimeout": 0,
			"protocolMappers": [
				{
					"id": "f0e819ab-ddae-400c-8410-85c536e7d333",
					"name": "locale",
					"protocol": "openid-connect",
					"protocolMapper": "oidc-usermodel-attribute-mapper",
					"consentRequired": false,
					"config": {
						"userinfo.token.claim": "true",
						"user.attribute": "locale",
						"id.token.claim": "true",
						"access.token.claim": "true",
						"claim.name": "locale",
						"jsonType.label": "String"
					}
				}
			],
			"defaultClientScopes": [
				"web-origins",
				"role_list",
				"roles",
				"profile",
				"email"
			],
			"optionalClientScopes": [
				"address",
				"phone",
				"offline_access",
				"microprofile-jwt"
			]
		}
	],
	"clientScopes": [
		{
			"id": "72038e13-52cd-4772-8401-fb99d63ed0b5",
			"name": "offline_access",
			"description": "OpenID Connect built-in scope: offline_access",
			"protocol": "openid-connect",
			"attributes": {
				"consent.screen.text": "${offlineAccessScopeConsentText}",
				"display.on.consent.screen": "true"
			}
		},
		{
			"id": "82c84a4c-7ec2-4c0e-9f9a-71e0b6bfb2a1",
			"name": "phone",
			"description": "OpenID Connect built-in scope: phone",
			"protocol": "openid-connect",
			"attributes": {
				"include.in.token.scope": "true",
				"display.on.consent.screen": "true",
				"consent.screen.text": "${phoneScopeConsentText}"
			},
			"protocolMappers": [
				{
					"id": "a5586ccc-1593-43aa-8f8a-642187c96cf9",
					"name": "phone number verified",
					"protocol": "openid-connect",
					"protocolMapper": "oidc-usermodel-attribute-mapper",
					"consentRequired": false,
					"config": {
						"userinfo.token.claim": "true",
						"user.attribute": "phoneNumberVerified",
						"id.token.claim": "true",
						"access.token.claim": "true",
						"claim.name": "phone_number_verified",
						"jsonType.label": "boolean"
					}
				},
				{
					"id": "8ff90ba8-c0fd-4062-900f-d18ed2208d9a",
					"name": "phone number",
					"protocol": "openid-connect",
					"protocolMapper": "oidc-usermodel-attribute-mapper",
					"consentRequired": false,
					"config": {
						"userinfo.token.claim": "true",
						"user.attribute": "phoneNumber",
						"id.token.claim": "true",
						"access.token.claim": "true",
						"claim.name": "phone_number",
						"jsonType.label": "String"
					}
				}
			]
		},
		{
			"id": "ec983bc7-3eff-453f-97b0-d0a987778b15",
			"name": "profile",
			"description": "OpenID Connect built-in scope: profile",
			"protocol": "openid-connect",
			"attributes": {
				"include.in.token.scope": "true",
				"display.on.consent.screen": "true",
				"consent.screen.text": "${profileScopeConsentText}"
			},
			"protocolMappers": [
				{
					"id": "8dd22363-6dcd-480f-bb04-a01a9d706161",
					"name": "locale",
					"protocol": "openid-connect",
					"protocolMapper": "oidc-usermodel-attribute-mapper",
					"consentRequired": false,
					"config": {
						"userinfo.token.claim": "true",
						"user.attribute": "locale",
						"id.token.claim": "true",
						"access.token.claim": "true",
						"claim.name": "locale",
						"jsonType.label": "String"
					}
				},
				{
					"id": "9eac2584-6f3e-4b0f-a11d-9b37257df6de",
					"name": "family name",
					"protocol": "openid-connect",
					"protocolMapper": "oidc-usermodel-property-mapper",
					"consentRequired": false,
					"config": {
						"userinfo.token.claim": "true",
						"user.attribute": "lastName",
						"id.token.claim": "true",
						"access.token.claim": "true",
						"claim.name": "family_name",
						"jsonType.label": "String"
					}
				},
				{
					"id": "1c86911d-e8a3-435e-b5df-bc801d6324e7",
					"name": "middle name",
					"protocol": "openid-connect",
					"protocolMapper": "oidc-usermodel-attribute-mapper",
					"consentRequired": false,
					"config": {
						"userinfo.token.claim": "true",
						"user.attribute": "middleName",
						"id.token.claim": "true",
						"access.token.claim": "true",
						"claim.name": "middle_name",
						"jsonType.label": "String"
					}
				},
				{
					"id": "aeaca2de-a9c0-410a-93af-c852622fe4ba",
					"name": "profile",
					"protocol": "openid-connect",
					"protocolMapper": "oidc-usermodel-attribute-mapper",
					"consentRequired": false,
					"config": {
						"userinfo.token.claim": "true",
						"user.attribute": "profile",
						"id.token.claim": "true",
						"access.token.claim": "true",
						"claim.name": "profile",
						"jsonType.label": "String"
					}
				},
				{
					"id": "ff3888ee-df66-4e36-b85c-65985075c8ad",
					"name": "given name",
					"protocol": "openid-connect",
					"protocolMapper": "oidc-usermodel-property-mapper",
					"consentRequired": false,
					"config": {
						"userinfo.token.claim": "true",
						"user.attribute": "firstName",
						"id.token.claim": "true",
						"access.token.claim": "true",
						"claim.name": "given_name",
						"jsonType.label": "String"
					}
				},
				{
					"id": "399fe6a1-d8cb-47d3-9f36-9f5baa223a8f",
					"name": "birthdate",
					"protocol": "openid-connect",
					"protocolMapper": "oidc-usermodel-attribute-mapper",
					"consentRequired": false,
					"config": {
						"userinfo.token.claim": "true",
						"user.attribute": "birthdate",
						"id.token.claim": "true",
						"access.token.claim": "true",
						"claim.name": "birthdate",
						"jsonType.label": "String"
					}
				},
				{
					"id": "fc7b6e12-77eb-46b3-891f-e6c7f947a85f",
					"name": "picture",
					"protocol": "openid-connect",
					"protocolMapper": "oidc-usermodel-attribute-mapper",
					"consentRequired": false,
					"config": {
						"userinfo.token.claim": "true",
						"user.attribute": "picture",
						"id.token.claim": "true",
						"access.token.claim": "true",
						"claim.name": "picture",
						"jsonType.label": "String"
					}
				},
				{
					"id": "33d35b3c-9175-4ca4-84d2-b74aafaff750",
					"name": "zoneinfo",
					"protocol": "openid-connect",
					"protocolMapper": "oidc-usermodel-attribute-mapper",
					"consentRequired": false,
					"config": {
						"userinfo.token.claim": "true",
						"user.attribute": "zoneinfo",
						"id.token.claim": "true",
						"access.token.claim": "true",
						"claim.name": "zoneinfo",
						"jsonType.label": "String"
					}
				},
				{
					"id": "21b5c884-650a-40af-adfd-7ab9f3963252",
					"name": "full name",
					"protocol": "openid-connect",
					"protocolMapper": "oidc-full-name-mapper",
					"consentRequired": false,
					"config": {
						"id.token.claim": "true",
						"access.token.claim": "true",
						"userinfo.token.claim": "true"
					}
				},
				{
					"id": "ee7982f6-7666-4d1f-9493-4cfbe043bdfd",
					"name": "gender",
					"protocol": "openid-connect",
					"protocolMapper": "oidc-usermodel-attribute-mapper",
					"consentRequired": false,
					"config": {
						"userinfo.token.claim": "true",
						"user.attribute": "gender",
						"id.token.claim": "true",
						"access.token.claim": "true",
						"claim.name": "gender",
						"jsonType.label": "String"
					}
				},
				{
					"id": "56182bb9-7936-4c1d-8a54-029348450416",
					"name": "username",
					"protocol": "openid-connect",
					"protocolMapper": "oidc-usermodel-property-mapper",
					"consentRequired": false,
					"config": {
						"userinfo.token.claim": "true",
						"user.attribute": "username",
						"id.token.claim": "true",
						"access.token.claim": "true",
						"claim.name": "preferred_username",
						"jsonType.label": "String"
					}
				},
				{
					"id": "81a6ea6f-c233-4bd5-95cf-b7743641504f",
					"name": "updated at",
					"protocol": "openid-connect",
					"protocolMapper": "oidc-usermodel-attribute-mapper",
					"consentRequired": false,
					"config": {
						"userinfo.token.claim": "true",
						"user.attribute": "updatedAt",
						"id.token.claim": "true",
						"access.token.claim": "true",
						"claim.name": "updated_at",
						"jsonType.label": "String"
					}
				},
				{
					"id": "3efb8ae2-3610-433a-99b6-60a38b2b79f4",
					"name": "nickname",
					"protocol": "openid-connect",
					"protocolMapper": "oidc-usermodel-attribute-mapper",
					"consentRequired": false,
					"config": {
						"userinfo.token.claim": "true",
						"user.attribute": "nickname",
						"id.token.claim": "true",
						"access.token.claim": "true",
						"claim.name": "nickname",
						"jsonType.label": "String"
					}
				},
				{
					"id": "a85c4bca-3f8b-44e1-a2be-f5172f82a5ea",
					"name": "website",
					"protocol": "openid-connect",
					"protocolMapper": "oidc-usermodel-attribute-mapper",
					"consentRequired": false,
					"config": {
						"userinfo.token.claim": "true",
						"user.attribute": "website",
						"id.token.claim": "true",
						"access.token.claim": "true",
						"claim.name": "website",
						"jsonType.label": "String"
					}
				}
			]
		},
		{
			"id": "a93058c4-177e-4010-9a05-4c1ec71cdba0",
			"name": "role_list",
			"description": "SAML role list",
			"protocol": "saml",
			"attributes": {
				"consent.screen.text": "${samlRoleListScopeConsentText}",
				"display.on.consent.screen": "true"
			},
			"protocolMappers": [
				{
					"id": "9b4854ef-9322-4195-acb7-2a2e3e3cc17e",
					"name": "role list",
					"protocol": "saml",
					"protocolMapper": "saml-role-list-mapper",
					"consentRequired": false,
					"config": {
						"single": "false",
						"attribute.nameformat": "Basic",
						"attribute.name": "Role"
					}
				}
			]
		},
		{
			"id": "8df3012a-7ae1-4056-a785-91c95aa50920",
			"name": "roles",
			"description": "OpenID Connect scope for add user roles to the access token",
			"protocol": "openid-connect",
			"attributes": {
				"include.in.token.scope": "false",
				"display.on.consent.screen": "true",
				"consent.screen.text": "${rolesScopeConsentText}"
			},
			"protocolMappers": [
				{
					"id": "92e4103d-f4b1-4798-a85c-85d75edf60bb",
					"name": "client roles",
					"protocol": "openid-connect",
					"protocolMapper": "oidc-usermodel-client-role-mapper",
					"consentRequired": false,
					"config": {
						"user.attribute": "foo",
						"access.token.claim": "true",
						"claim.name": "resource_access.${client_id}.roles",
						"jsonType.label": "String",
						"multivalued": "true"
					}
				},
				{
					"id": "48d8f59a-1fdd-4f06-8cae-39fe76af9f0c",
					"name": "audience resolve",
					"protocol": "openid-connect",
					"protocolMapper": "oidc-audience-resolve-mapper",
					"consentRequired": false,
					"config": {}
				},
				{
					"id": "ac8a9b88-3568-43c5-986a-c39172b8c845",
					"name": "realm roles",
					"protocol": "openid-connect",
					"protocolMapper": "oidc-usermodel-realm-role-mapper",
					"consentRequired": false,
					"config": {
						"user.attribute": "foo",
						"access.token.claim": "true",
						"claim.name": "realm_access.roles",
						"jsonType.label": "String",
						"multivalued": "true"
					}
				}
			]
		},
		{
			"id": "03ca17e2-d4ec-4e46-8b51-0e7fddc7d94e",
			"name": "web-origins",
			"description": "OpenID Connect scope for add allowed web origins to the access token",
			"protocol": "openid-connect",
			"attributes": {
				"include.in.token.scope": "false",
				"display.on.consent.screen": "false",
				"consent.screen.text": ""
			},
			"protocolMappers": [
				{
					"id": "3b7cfa8f-09da-40e7-a21b-4fd7f60de0db",
					"name": "allowed web origins",
					"protocol": "openid-connect",
					"protocolMapper": "oidc-allowed-origins-mapper",
					"consentRequired": false,
					"config": {}
				}
			]
		},
		{
			"id": "e9fdd669-8ce5-4474-be7e-adf73801a457",
			"name": "address",
			"description": "OpenID Connect built-in scope: address",
			"protocol": "openid-connect",
			"attributes": {
				"include.in.token.scope": "true",
				"display.on.consent.screen": "true",
				"consent.screen.text": "${addressScopeConsentText}"
			},
			"protocolMappers": [
				{
					"id": "9e8824a1-f378-4d6a-b70b-43c205350122",
					"name": "address",
					"protocol": "openid-connect",
					"protocolMapper": "oidc-address-mapper",
					"consentRequired": false,
					"config": {
						"user.attribute.formatted": "formatted",
						"user.attribute.country": "country",
						"user.attribute.postal_code": "postal_code",
						"userinfo.token.claim": "true",
						"user.attribute.street": "street",
						"id.token.claim": "true",
						"user.attribute.region": "region",
						"access.token.claim": "true",
						"user.attribute.locality": "locality"
					}
				}
			]
		},
		{
			"id": "c30c721f-c158-455c-9882-a818e95d05ca",
			"name": "email",
			"description": "OpenID Connect built-in scope: email",
			"protocol": "openid-connect",
			"attributes": {
				"include.in.token.scope": "true",
				"display.on.consent.screen": "true",
				"consent.screen.text": "${emailScopeConsentText}"
			},
			"protocolMappers": [
				{
					"id": "f933cb2f-d39e-44df-a613-4ecb50adfd19",
					"name": "email verified",
					"protocol": "openid-connect",
					"protocolMapper": "oidc-usermodel-property-mapper",
					"consentRequired": false,
					"config": {
						"userinfo.token.claim": "true",
						"user.attribute": "emailVerified",
						"id.token.claim": "true",
						"access.token.claim": "true",
						"claim.name": "email_verified",
						"jsonType.label": "boolean"
					}
				},
				{
					"id": "9cbdb362-7448-488d-9169-b25c2c9f3fe3",
					"name": "email",
					"protocol": "openid-connect",
					"protocolMapper": "oidc-usermodel-property-mapper",
					"consentRequired": false,
					"config": {
						"userinfo.token.claim": "true",
						"user.attribute": "email",
						"id.token.claim": "true",
						"access.token.claim": "true",
						"claim.name": "email",
						"jsonType.label": "String"
					}
				}
			]
		},
		{
			"id": "f3ae178f-3f27-4587-b645-91e3898848c6",
			"name": "microprofile-jwt",
			"description": "Microprofile - JWT built-in scope",
			"protocol": "openid-connect",
			"attributes": {
				"include.in.token.scope": "true",
				"display.on.consent.screen": "false"
			},
			"protocolMappers": [
				{
					"id": "12c515b3-b69b-4cf5-a3de-d76cfc188612",
					"name": "upn",
					"protocol": "openid-connect",
					"protocolMapper": "oidc-usermodel-property-mapper",
					"consentRequired": false,
					"config": {
						"userinfo.token.claim": "true",
						"user.attribute": "username",
						"id.token.claim": "true",
						"access.token.claim": "true",
						"claim.name": "upn",
						"jsonType.label": "String"
					}
				},
				{
					"id": "1cb7dee4-caa8-42e2-a444-29aab7109b9c",
					"name": "groups",
					"protocol": "openid-connect",
					"protocolMapper": "oidc-usermodel-realm-role-mapper",
					"consentRequired": false,
					"config": {
						"multivalued": "true",
						"userinfo.token.claim": "true",
						"user.attribute": "foo",
						"id.token.claim": "true",
						"access.token.claim": "true",
						"claim.name": "groups",
						"jsonType.label": "String"
					}
				}
			]
		}
	],
	"defaultDefaultClientScopes": [
		"web-origins",
		"roles",
		"role_list",
		"email",
		"profile"
	],
	"defaultOptionalClientScopes": [
		"offline_access",
		"phone",
		"address",
		"microprofile-jwt"
	],
	"browserSecurityHeaders": {
		"contentSecurityPolicyReportOnly": "",
		"xContentTypeOptions": "nosniff",
		"xRobotsTag": "none",
		"xFrameOptions": "SAMEORIGIN",
		"contentSecurityPolicy": "frame-src 'self'; frame-ancestors 'self'; object-src 'none';",
		"xXSSProtection": "1; mode=block",
		"strictTransportSecurity": "max-age=31536000; includeSubDomains"
	},
	"smtpServer": {},
	"eventsEnabled": false,
	"eventsListeners": ["jboss-logging"],
	"enabledEventTypes": [],
	"adminEventsEnabled": false,
	"adminEventsDetailsEnabled": false,
	"identityProviders": [],
	"identityProviderMappers": [],
	"components": {
		"org.keycloak.services.clientregistration.policy.ClientRegistrationPolicy": [
			{
				"id": "3b96a4b2-cf82-4a04-8664-f9915d864719",
				"name": "Full Scope Disabled",
				"providerId": "scope",
				"subType": "anonymous",
				"subComponents": {},
				"config": {}
			},
			{
				"id": "6a4a56f5-979a-48bc-beae-772830ac549e",
				"name": "Trusted Hosts",
				"providerId": "trusted-hosts",
				"subType": "anonymous",
				"subComponents": {},
				"config": {
					"host-sending-registration-request-must-match": ["true"],
					"client-uris-must-match": ["true"]
				}
			},
			{
				"id": "b63a3a3e-3224-443a-ac80-15ff651fd26d",
				"name": "Allowed Client Scopes",
				"providerId": "allowed-client-templates",
				"subType": "authenticated",
				"subComponents": {},
				"config": {
					"allow-default-scopes": ["true"]
				}
			},
			{
				"id": "d0f6e610-820c-457c-84d0-38e3f3ba044f",
				"name": "Consent Required",
				"providerId": "consent-required",
				"subType": "anonymous",
				"subComponents": {},
				"config": {}
			},
			{
				"id": "96c227bd-4e18-406b-b68b-ac54261258e3",
				"name": "Allowed Protocol Mapper Types",
				"providerId": "allowed-protocol-mappers",
				"subType": "anonymous",
				"subComponents": {},
				"config": {
					"allowed-protocol-mapper-types": [
						"oidc-usermodel-attribute-mapper",
						"oidc-address-mapper",
						"saml-user-property-mapper",
						"oidc-full-name-mapper",
						"oidc-sha256-pairwise-sub-mapper",
						"saml-user-attribute-mapper",
						"oidc-usermodel-property-mapper",
						"saml-role-list-mapper"
					]
				}
			},
			{
				"id": "0be6c588-e054-4cb7-aefc-6dd98c9f6206",
				"name": "Allowed Protocol Mapper Types",
				"providerId": "allowed-protocol-mappers",
				"subType": "authenticated",
				"subComponents": {},
				"config": {
					"allowed-protocol-mapper-types": [
						"saml-user-attribute-mapper",
						"oidc-usermodel-attribute-mapper",
						"saml-role-list-mapper",
						"oidc-usermodel-property-mapper",
						"oidc-sha256-pairwise-sub-mapper",
						"oidc-full-name-mapper",
						"oidc-address-mapper",
						"saml-user-property-mapper"
					]
				}
			},
			{
				"id": "47edaa72-c7c1-412d-9d43-2a114cb1d7a4",
				"name": "Allowed Client Scopes",
				"providerId": "allowed-client-templates",
				"subType": "anonymous",
				"subComponents": {},
				"config": {
					"allow-default-scopes": ["true"]
				}
			},
			{
				"id": "da6c0a6f-d7c0-4c48-921e-682f6e53c110",
				"name": "Max Clients Limit",
				"providerId": "max-clients",
				"subType": "anonymous",
				"subComponents": {},
				"config": {
					"max-clients": ["200"]
				}
			}
		],
		"org.keycloak.keys.KeyProvider": [
			{
				"id": "acb947ff-3c11-4298-a698-a48e5175f793",
				"name": "rsa-generated",
				"providerId": "rsa-generated",
				"subComponents": {},
				"config": {
					"priority": ["100"]
				}
			},
			{
				"id": "c4ade590-aaab-4648-9353-d7d24e4d25a9",
				"name": "aes-generated",
				"providerId": "aes-generated",
				"subComponents": {},
				"config": {
					"priority": ["100"]
				}
			},
			{
				"id": "76fe11a5-86d4-4a20-9639-f54298e7d9b4",
				"name": "hmac-generated",
				"providerId": "hmac-generated",
				"subComponents": {},
				"config": {
					"priority": ["100"],
					"algorithm": ["HS256"]
				}
			}
		]
	},
	"internationalizationEnabled": false,
	"supportedLocales": [],
	"authenticationFlows": [
		{
			"id": "5826e2c5-d882-4c67-bd9f-099caa4d591f",
			"alias": "Account verification options",
			"description": "Method with which to verity the existing account",
			"providerId": "basic-flow",
			"topLevel": false,
			"builtIn": true,
			"authenticationExecutions": [
				{
					"authenticator": "idp-email-verification",
					"requirement": "ALTERNATIVE",
					"priority": 10,
					"userSetupAllowed": false,
					"autheticatorFlow": false
				},
				{
					"requirement": "ALTERNATIVE",
					"priority": 20,
					"flowAlias": "Verify Existing Account by Re-authentication",
					"userSetupAllowed": false,
					"autheticatorFlow": true
				}
			]
		},
		{
			"id": "0047a9c7-c034-4865-aff6-05d43941bb4e",
			"alias": "Authentication Options",
			"description": "Authentication options.",
			"providerId": "basic-flow",
			"topLevel": false,
			"builtIn": true,
			"authenticationExecutions": [
				{
					"authenticator": "basic-auth",
					"requirement": "REQUIRED",
					"priority": 10,
					"userSetupAllowed": false,
					"autheticatorFlow": false
				},
				{
					"authenticator": "basic-auth-otp",
					"requirement": "DISABLED",
					"priority": 20,
					"userSetupAllowed": false,
					"autheticatorFlow": false
				},
				{
					"authenticator": "auth-spnego",
					"requirement": "DISABLED",
					"priority": 30,
					"userSetupAllowed": false,
					"autheticatorFlow": false
				}
			]
		},
		{
			"id": "7ee08f4f-4cd4-49b0-a792-7d78e6392339",
			"alias": "Browser - Conditional OTP",
			"description": "Flow to determine if the OTP is required for the authentication",
			"providerId": "basic-flow",
			"topLevel": false,
			"builtIn": true,
			"authenticationExecutions": [
				{
					"authenticator": "conditional-user-configured",
					"requirement": "REQUIRED",
					"priority": 10,
					"userSetupAllowed": false,
					"autheticatorFlow": false
				},
				{
					"authenticator": "auth-otp-form",
					"requirement": "REQUIRED",
					"priority": 20,
					"userSetupAllowed": false,
					"autheticatorFlow": false
				}
			]
		},
		{
			"id": "4703aafb-fe36-4fab-a925-4cb915721cdc",
			"alias": "Direct Grant - Conditional OTP",
			"description": "Flow to determine if the OTP is required for the authentication",
			"providerId": "basic-flow",
			"topLevel": false,
			"builtIn": true,
			"authenticationExecutions": [
				{
					"authenticator": "conditional-user-configured",
					"requirement": "REQUIRED",
					"priority": 10,
					"userSetupAllowed": false,
					"autheticatorFlow": false
				},
				{
					"authenticator": "direct-grant-validate-otp",
					"requirement": "REQUIRED",
					"priority": 20,
					"userSetupAllowed": false,
					"autheticatorFlow": false
				}
			]
		},
		{
			"id": "3a2f962d-cd37-4fdd-94a3-dd7049a494a6",
			"alias": "First broker login - Conditional OTP",
			"description": "Flow to determine if the OTP is required for the authentication",
			"providerId": "basic-flow",
			"topLevel": false,
			"builtIn": true,
			"authenticationExecutions": [
				{
					"authenticator": "conditional-user-configured",
					"requirement": "REQUIRED",
					"priority": 10,
					"userSetupAllowed": false,
					"autheticatorFlow": false
				},
				{
					"authenticator": "auth-otp-form",
					"requirement": "REQUIRED",
					"priority": 20,
					"userSetupAllowed": false,
					"autheticatorFlow": false
				}
			]
		},
		{
			"id": "7781a8a5-cb29-47e1-9a60-e422b8f01697",
			"alias": "Handle Existing Account",
			"description": "Handle what to do if there is existing account with same email/username like authenticated identity provider",
			"providerId": "basic-flow",
			"topLevel": false,
			"builtIn": true,
			"authenticationExecutions": [
				{
					"authenticator": "idp-confirm-link",
					"requirement": "REQUIRED",
					"priority": 10,
					"userSetupAllowed": false,
					"autheticatorFlow": false
				},
				{
					"requirement": "REQUIRED",
					"priority": 20,
					"flowAlias": "Account verification options",
					"userSetupAllowed": false,
					"autheticatorFlow": true
				}
			]
		},
		{
			"id": "90500e42-2020-4c83-8556-0396c72e50d9",
			"alias": "Reset - Conditional OTP",
			"description": "Flow to determine if the OTP should be reset or not. Set to REQUIRED to force.",
			"providerId": "basic-flow",
			"topLevel": false,
			"builtIn": true,
			"authenticationExecutions": [
				{
					"authenticator": "conditional-user-configured",
					"requirement": "REQUIRED",
					"priority": 10,
					"userSetupAllowed": false,
					"autheticatorFlow": false
				},
				{
					"authenticator": "reset-otp",
					"requirement": "REQUIRED",
					"priority": 20,
					"userSetupAllowed": false,
					"autheticatorFlow": false
				}
			]
		},
		{
			"id": "2f918e03-ac3d-4fad-8f18-d8331e326377",
			"alias": "User creation or linking",
			"description": "Flow for the existing/non-existing user alternatives",
			"providerId": "basic-flow",
			"topLevel": false,
			"builtIn": true,
			"authenticationExecutions": [
				{
					"authenticatorConfig": "create unique user config",
					"authenticator": "idp-create-user-if-unique",
					"requirement": "ALTERNATIVE",
					"priority": 10,
					"userSetupAllowed": false,
					"autheticatorFlow": false
				},
				{
					"requirement": "ALTERNATIVE",
					"priority": 20,
					"flowAlias": "Handle Existing Account",
					"userSetupAllowed": false,
					"autheticatorFlow": true
				}
			]
		},
		{
			"id": "1849266a-007e-4ff6-aa33-a7b386d88e1f",
			"alias": "Verify Existing Account by Re-authentication",
			"description": "Reauthentication of existing account",
			"providerId": "basic-flow",
			"topLevel": false,
			"builtIn": true,
			"authenticationExecutions": [
				{
					"authenticator": "idp-username-password-form",
					"requirement": "REQUIRED",
					"priority": 10,
					"userSetupAllowed": false,
					"autheticatorFlow": false
				},
				{
					"requirement": "CONDITIONAL",
					"priority": 20,
					"flowAlias": "First broker login - Conditional OTP",
					"userSetupAllowed": false,
					"autheticatorFlow": true
				}
			]
		},
		{
			"id": "dd50db2a-3c57-42c2-8744-913ef9de9061",
			"alias": "browser",
			"description": "browser based authentication",
			"providerId": "basic-flow",
			"topLevel": true,
			"builtIn": true,
			"authenticationExecutions": [
				{
					"authenticator": "auth-cookie",
					"requirement": "ALTERNATIVE",
					"priority": 10,
					"userSetupAllowed": false,
					"autheticatorFlow": false
				},
				{
					"authenticator": "auth-spnego",
					"requirement": "DISABLED",
					"priority": 20,
					"userSetupAllowed": false,
					"autheticatorFlow": false
				},
				{
					"authenticator": "identity-provider-redirector",
					"requirement": "ALTERNATIVE",
					"priority": 25,
					"userSetupAllowed": false,
					"autheticatorFlow": false
				},
				{
					"requirement": "ALTERNATIVE",
					"priority": 30,
					"flowAlias": "forms",
					"userSetupAllowed": false,
					"autheticatorFlow": true
				}
			]
		},
		{
			"id": "2e7bbe9e-442a-44e2-a5b2-4709ff5e40e1",
			"alias": "clients",
			"description": "Base authentication for clients",
			"providerId": "client-flow",
			"topLevel": true,
			"builtIn": true,
			"authenticationExecutions": [
				{
					"authenticator": "client-secret",
					"requirement": "ALTERNATIVE",
					"priority": 10,
					"userSetupAllowed": false,
					"autheticatorFlow": false
				},
				{
					"authenticator": "client-jwt",
					"requirement": "ALTERNATIVE",
					"priority": 20,
					"userSetupAllowed": false,
					"autheticatorFlow": false
				},
				{
					"authenticator": "client-secret-jwt",
					"requirement": "ALTERNATIVE",
					"priority": 30,
					"userSetupAllowed": false,
					"autheticatorFlow": false
				},
				{
					"authenticator": "client-x509",
					"requirement": "ALTERNATIVE",
					"priority": 40,
					"userSetupAllowed": false,
					"autheticatorFlow": false
				}
			]
		},
		{
			"id": "d6135db7-fa8f-45a5-aeaf-e70d01eeef19",
			"alias": "direct grant",
			"description": "OpenID Connect Resource Owner Grant",
			"providerId": "basic-flow",
			"topLevel": true,
			"builtIn": true,
			"authenticationExecutions": [
				{
					"authenticator": "direct-grant-validate-username",
					"requirement": "REQUIRED",
					"priority": 10,
					"userSetupAllowed": false,
					"autheticatorFlow": false
				},
				{
					"authenticator": "direct-grant-validate-password",
					"requirement": "REQUIRED",
					"priority": 20,
					"userSetupAllowed": false,
					"autheticatorFlow": false
				},
				{
					"requirement": "CONDITIONAL",
					"priority": 30,
					"flowAlias": "Direct Grant - Conditional OTP",
					"userSetupAllowed": false,
					"autheticatorFlow": true
				}
			]
		},
		{
			"id": "38a88d9a-3a53-4419-b6dc-82dc4cff5925",
			"alias": "docker auth",
			"description": "Used by Docker clients to authenticate against the IDP",
			"providerId": "basic-flow",
			"topLevel": true,
			"builtIn": true,
			"authenticationExecutions": [
				{
					"authenticator": "docker-http-basic-authenticator",
					"requirement": "REQUIRED",
					"priority": 10,
					"userSetupAllowed": false,
					"autheticatorFlow": false
				}
			]
		},
		{
			"id": "6bdb3477-a69c-4a33-b6e0-28a76d162151",
			"alias": "first broker login",
			"description": "Actions taken after first broker login with identity provider account, which is not yet linked to any Keycloak account",
			"providerId": "basic-flow",
			"topLevel": true,
			"builtIn": true,
			"authenticationExecutions": [
				{
					"authenticatorConfig": "review profile config",
					"authenticator": "idp-review-profile",
					"requirement": "REQUIRED",
					"priority": 10,
					"userSetupAllowed": false,
					"autheticatorFlow": false
				},
				{
					"requirement": "REQUIRED",
					"priority": 20,
					"flowAlias": "User creation or linking",
					"userSetupAllowed": false,
					"autheticatorFlow": true
				}
			]
		},
		{
			"id": "85b67adb-219b-4254-92d5-e97f3fdede38",
			"alias": "forms",
			"description": "Username, password, otp and other auth forms.",
			"providerId": "basic-flow",
			"topLevel": false,
			"builtIn": true,
			"authenticationExecutions": [
				{
					"authenticator": "auth-username-password-form",
					"requirement": "REQUIRED",
					"priority": 10,
					"userSetupAllowed": false,
					"autheticatorFlow": false
				},
				{
					"requirement": "CONDITIONAL",
					"priority": 20,
					"flowAlias": "Browser - Conditional OTP",
					"userSetupAllowed": false,
					"autheticatorFlow": true
				}
			]
		},
		{
			"id": "818d2a32-7a18-4435-a4d9-66f12b0a0575",
			"alias": "http challenge",
			"description": "An authentication flow based on challenge-response HTTP Authentication Schemes",
			"providerId": "basic-flow",
			"topLevel": true,
			"builtIn": true,
			"authenticationExecutions": [
				{
					"authenticator": "no-cookie-redirect",
					"requirement": "REQUIRED",
					"priority": 10,
					"userSetupAllowed": false,
					"autheticatorFlow": false
				},
				{
					"requirement": "REQUIRED",
					"priority": 20,
					"flowAlias": "Authentication Options",
					"userSetupAllowed": false,
					"autheticatorFlow": true
				}
			]
		},
		{
			"id": "d859b94c-3d93-4821-b1cf-bff577b1c88c",
			"alias": "registration",
			"description": "registration flow",
			"providerId": "basic-flow",
			"topLevel": true,
			"builtIn": true,
			"authenticationExecutions": [
				{
					"authenticator": "registration-page-form",
					"requirement": "REQUIRED",
					"priority": 10,
					"flowAlias": "registration form",
					"userSetupAllowed": false,
					"autheticatorFlow": true
				}
			]
		},
		{
			"id": "8d43dcd0-7c64-4ba5-8feb-66a2f6b7478e",
			"alias": "registration form",
			"description": "registration form",
			"providerId": "form-flow",
			"topLevel": false,
			"builtIn": true,
			"authenticationExecutions": [
				{
					"authenticator": "registration-user-creation",
					"requirement": "REQUIRED",
					"priority": 20,
					"userSetupAllowed": false,
					"autheticatorFlow": false
				},
				{
					"authenticator": "registration-profile-action",
					"requirement": "REQUIRED",
					"priority": 40,
					"userSetupAllowed": false,
					"autheticatorFlow": false
				},
				{
					"authenticator": "registration-password-action",
					"requirement": "REQUIRED",
					"priority": 50,
					"userSetupAllowed": false,
					"autheticatorFlow": false
				},
				{
					"authenticator": "registration-recaptcha-action",
					"requirement": "DISABLED",
					"priority": 60,
					"userSetupAllowed": false,
					"autheticatorFlow": false
				}
			]
		},
		{
			"id": "fc666b63-fec2-430b-9d32-ca1d235d8b53",
			"alias": "reset credentials",
			"description": "Reset credentials for a user if they forgot their password or something",
			"providerId": "basic-flow",
			"topLevel": true,
			"builtIn": true,
			"authenticationExecutions": [
				{
					"authenticator": "reset-credentials-choose-user",
					"requirement": "REQUIRED",
					"priority": 10,
					"userSetupAllowed": false,
					"autheticatorFlow": false
				},
				{
					"authenticator": "reset-credential-email",
					"requirement": "REQUIRED",
					"priority": 20,
					"userSetupAllowed": false,
					"autheticatorFlow": false
				},
				{
					"authenticator": "reset-password",
					"requirement": "REQUIRED",
					"priority": 30,
					"userSetupAllowed": false,
					"autheticatorFlow": false
				},
				{
					"requirement": "CONDITIONAL",
					"priority": 40,
					"flowAlias": "Reset - Conditional OTP",
					"userSetupAllowed": false,
					"autheticatorFlow": true
				}
			]
		},
		{
			"id": "002b4b5a-aaa1-4a11-9dfd-50266f8b2e4f",
			"alias": "saml ecp",
			"description": "SAML ECP Profile Authentication Flow",
			"providerId": "basic-flow",
			"topLevel": true,
			"builtIn": true,
			"authenticationExecutions": [
				{
					"authenticator": "http-basic-authenticator",
					"requirement": "REQUIRED",
					"priority": 10,
					"userSetupAllowed": false,
					"autheticatorFlow": false
				}
			]
		}
	],
	"authenticatorConfig": [
		{
			"id": "aae8e203-ec81-4f91-9d03-f3f2d10d9305",
			"alias": "create unique user config",
			"config": {
				"require.password.update.after.registration": "false"
			}
		},
		{
			"id": "275762e3-12c9-41c9-a741-30a75119015d",
			"alias": "review profile config",
			"config": {
				"update.profile.on.first.login": "missing"
			}
		}
	],
	"requiredActions": [
		{
			"alias": "CONFIGURE_TOTP",
			"name": "Configure OTP",
			"providerId": "CONFIGURE_TOTP",
			"enabled": true,
			"defaultAction": false,
			"priority": 10,
			"config": {}
		},
		{
			"alias": "terms_and_conditions",
			"name": "Terms and Conditions",
			"providerId": "terms_and_conditions",
			"enabled": false,
			"defaultAction": false,
			"priority": 20,
			"config": {}
		},
		{
			"alias": "UPDATE_PASSWORD",
			"name": "Update Password",
			"providerId": "UPDATE_PASSWORD",
			"enabled": true,
			"defaultAction": false,
			"priority": 30,
			"config": {}
		},
		{
			"alias": "UPDATE_PROFILE",
			"name": "Update Profile",
			"providerId": "UPDATE_PROFILE",
			"enabled": true,
			"defaultAction": false,
			"priority": 40,
			"config": {}
		},
		{
			"alias": "VERIFY_EMAIL",
			"name": "Verify Email",
			"providerId": "VERIFY_EMAIL",
			"enabled": true,
			"defaultAction": false,
			"priority": 50,
			"config": {}
		},
		{
			"alias": "delete_account",
			"name": "Delete Account",
			"providerId": "delete_account",
			"enabled": false,
			"defaultAction": false,
			"priority": 60,
			"config": {}
		},
		{
			"alias": "update_user_locale",
			"name": "Update User Locale",
			"providerId": "update_user_locale",
			"enabled": true,
			"defaultAction": false,
			"priority": 1000,
			"config": {}
		}
	],
	"browserFlow": "browser",
	"registrationFlow": "registration",
	"directGrantFlow": "direct grant",
	"resetCredentialsFlow": "reset credentials",
	"clientAuthenticationFlow": "clients",
	"dockerAuthenticationFlow": "docker auth",
	"attributes": {
		"clientOfflineSessionMaxLifespan": "0",
		"clientSessionIdleTimeout": "0",
		"clientSessionMaxLifespan": "0",
		"clientOfflineSessionIdleTimeout": "0"
	},
	"keycloakVersion": "12.0.4",
	"userManagedAccessAllowed": false
}
